dpk_connector/__init__.py
dpk_connector/core/__init__.py
dpk_connector/core/crawler.py
dpk_connector/core/item.py
dpk_connector/core/logging.py
dpk_connector/core/middlewares.py
dpk_connector/core/pipelines.py
dpk_connector/core/settings.py
dpk_connector/core/utils.py
dpk_connector/core/spiders/__init__.py
dpk_connector/core/spiders/sitemap.py
data_prep_connector-0.2.3.dist-info/METADATA
data_prep_connector-0.2.3.dist-info/WHEEL
data_prep_connector-0.2.3.dist-info/top_level.txt
data_prep_connector-0.2.3.dist-info/RECORD
