Metadata-Version: 2.1
Name: data_prep_connector
Version: 0.2.3
Summary: Scalable and Compliant Web Crawler
Author-email: Hiroya Matsubara <hmtbr@jp.ibm.com>
License: Apache-2.0
Keywords: data,data acquisition,crawler,web crawler,llm,generative,ai,fine-tuning,llmapps,0b74b5a
Requires-Python: <3.13,>=3.10
Requires-Dist: scrapy>=2.11.2
Requires-Dist: pydantic>=2.8.1
Requires-Dist: tldextract>=5.1.2
Provides-Extra: dev
Requires-Dist: twine; extra == "dev"
Requires-Dist: pytest>=7.3.2; extra == "dev"
Requires-Dist: pytest-dotenv>=0.5.2; extra == "dev"
Requires-Dist: pytest-env>=1.0.0; extra == "dev"
Requires-Dist: pre-commit>=3.3.2; extra == "dev"
Requires-Dist: pytest-cov>=4.1.0; extra == "dev"
Requires-Dist: pytest-mock>=3.10.0; extra == "dev"
Requires-Dist: pytest-datadir>=1.5.0; extra == "dev"
Requires-Dist: moto==5.0.5; extra == "dev"
Requires-Dist: markupsafe==2.0.1; extra == "dev"
